{
  "Architecture": "x86_64",
  "Build Date": "Wed 21 Jul 2021 18:42:03 BST",
  "Conflicts With": "None",
  "Depends On": "glibc",
  "Description": "A terminal based graphical activity monitor inspired by gtop and vtop",
  "Download Size": "2.71 MiB",
  "Groups": "None",
  "Installed Size": "7.59 MiB",
  "Licenses": "MIT",
  "Name": "gotop",
  "Optional Deps": "None",
  "Packager": "Wayne Wesley <wayne6324@gmail.com>",
  "Provides": "None",
  "Replaces": "None",
  "Repository": "therepoclub",
  "URL": "https://github.com/xxxserxxx/gotop",
  "Validated By": [
    "MD5 Sum",
    "SHA-256 Sum",
    "Signature"
  ],
  "Version": "4.1.2-1"
}