{
  "Architecture": "any",
  "Build Date": "Fri 09 Sep 2022 12:43:33 UTC",
  "Conflicts With": "None",
  "Depends On": "None",
  "Description": "linuxrepos keyring",
  "Download Size": "10.58 KiB",
  "Groups": "therepoclub",
  "Installed Size": "0.00 KiB",
  "Licenses": "GPL3",
  "Name": "linuxrepos-keyring",
  "Optional Deps": "None",
  "Packager": "Wayne Wesley <wayne6324@gmail.com>",
  "Provides": "None",
  "Replaces": "None",
  "Repository": "linuxrepos",
  "URL": "https://github.com/ArchAUR/linuxrepos-keyring",
  "Validated By": [
    "MD5 Sum",
    "SHA-256 Sum",
    "Signature"
  ],
  "Version": "2022.09.09-1"
}