{
  "Architecture": "x86_64",
  "Build Date": "Sat 09 Mar 2024 12:54:15 UTC",
  "Conflicts With": "None",
  "Depends On": [
    "pacman>5",
    "git"
  ],
  "Description": "Yet another yogurt. Pacman wrapper and AUR helper written in go.",
  "Download Size": "3.64 MiB",
  "Groups": "None",
  "Installed Size": "9.34 MiB",
  "Licenses": "GPL-3.0-or-later",
  "Name": "yay",
  "Optional Deps": {
    "doas": "privilege elevation",
    "sudo": "privilege elevation"
  },
  "Packager": "Wayne Wesley <wayne6324@gmail.com>",
  "Provides": "None",
  "Replaces": "None",
  "Repository": "linuxrepos",
  "URL": "https://github.com/Jguer/yay",
  "Validated By": [
    "MD5 Sum",
    "SHA-256 Sum",
    "Signature"
  ],
  "Version": "12.3.1-1"
}